<?xml version="1.0" encoding="UTF-8"?>

<CHAT xmlns:xsi="http://www.w3.org/2001/XMLSchema-instance"
      xmlns="http://www.talkbank.org/ns/talkbank"
      xsi:schemaLocation="http://www.talkbank.org/ns/talkbank https://talkbank.org/software/talkbank.xsd"
      Version="3.2.3"
      Lang="fra"
      Corpus="corpus"
      >
  <Participants>
    <participant
      id="CHI"
      role="Child"
      language="fra"
      age="P2Y06M"

    />
    <participant
      id="MOT"
      role="Mother"
      language="fra"

    />
  </Participants>
  <comment type="Generic">Phonological tier with pho group delimiters and complex groupings</comment>
  <comment type="Generic">Constructs: pho_groups with grouping brackets</comment>
  <u who="CHI" uID="u0">
    <w>A<pho xmlns="http://www.talkbank.org/ns/talkbank"><pw><ph><base>a</base></ph></pw><pw><ph><base>b</base></ph></pw></pho></w>
    <w>B<pho xmlns="http://www.talkbank.org/ns/talkbank"><pw><ph><base>c</base></ph></pw></pho></w>
    <w>C<pho xmlns="http://www.talkbank.org/ns/talkbank"><pw><ph><base>d</base></ph></pw><pw><ph><base>e</base></ph></pw></pho></w>
    <w>D<pho xmlns="http://www.talkbank.org/ns/talkbank"><pw><ph><base>f</base></ph></pw></pho></w>
    <w>E<pho xmlns="http://www.talkbank.org/ns/talkbank"><pw><ph><base>g</base></ph></pw></pho></w>
    <t type="p"></t>

  </u>
</CHAT>